wiverno/__init__.py
wiverno/cli.py
wiverno/main.py
wiverno/core/__init__.py
wiverno/core/config.py
wiverno/core/default_pages.py
wiverno/core/exceptions.py
wiverno/core/requests.py
wiverno/core/server.py
wiverno/core/http/validator.py
wiverno/core/routing/__init__.py
wiverno/core/routing/base.py
wiverno/core/routing/patterns.py
wiverno/core/routing/registry.py
wiverno/core/routing/router.py
wiverno/dev/__init__.py
wiverno/dev/dev_server.py
wiverno/static/templates/error_404.html
wiverno/static/templates/error_405.html
wiverno/static/templates/error_500.html
wiverno/templating/__init__.py
wiverno/templating/templator.py
wiverno/views/base_views.py
wiverno-1.0.3.dist-info/METADATA
wiverno-1.0.3.dist-info/WHEEL
wiverno-1.0.3.dist-info/entry_points.txt
wiverno-1.0.3.dist-info/licenses/LICENSE
wiverno-1.0.3.dist-info/RECORD
