Metadata-Version: 2.4
Name: wiverno
Version: 1.0.3
Summary: A lightweight WSGI framework for building fast and flexible Python web applications
Author: Sayrrexe
License-Expression: MIT
License-File: LICENSE
Keywords: framework,web,wsgi
Classifier: Development Status :: 3 - Alpha
Classifier: Intended Audience :: Developers
Classifier: License :: OSI Approved :: MIT License
Classifier: Programming Language :: Python :: 3
Classifier: Programming Language :: Python :: 3.12
Classifier: Programming Language :: Python :: 3.13
Classifier: Topic :: Internet :: WWW/HTTP
Classifier: Topic :: Software Development :: Libraries :: Application Frameworks
Requires-Python: >=3.12
Requires-Dist: jinja2>=3.1.0
Requires-Dist: rich>=13.7.0
Requires-Dist: typer>=0.12.0
Requires-Dist: watchdog>=4.0.0
Provides-Extra: dev
Requires-Dist: mkdocs-material>=9.5.0; extra == 'dev'
Requires-Dist: mkdocstrings[python]>=0.25.0; extra == 'dev'
Requires-Dist: mypy>=1.11.0; extra == 'dev'
Requires-Dist: pre-commit>=3.8.0; extra == 'dev'
Requires-Dist: pytest-benchmark>=4.0.0; extra == 'dev'
Requires-Dist: pytest-cov>=4.1.0; extra == 'dev'
Requires-Dist: pytest>=8.0.0; extra == 'dev'
Requires-Dist: python-dotenv>=1.0.0; extra == 'dev'
Requires-Dist: ruff>=0.6.0; extra == 'dev'
